brant_csv_converter/__init__.py
brant_csv_converter/converter.py
brant_csv_converter-0.1.0.dist-info/entry_points.txt
brant_csv_converter-0.1.0.dist-info/WHEEL
brant_csv_converter-0.1.0.dist-info/METADATA
brant_csv_converter-0.1.0.dist-info/RECORD
