Metadata-Version: 2.1
Name: brant-csv-converter
Version: 0.1.0
Summary: Program that convert a archive csv to json and json to csv
Author: Bruno Brant
Author-email: bruno.tombrant@gmail.com
Requires-Python: >=3.8,<4.0
Classifier: Programming Language :: Python :: 3
Classifier: Programming Language :: Python :: 3.10
Classifier: Programming Language :: Python :: 3.8
Classifier: Programming Language :: Python :: 3.9
Requires-Dist: click (>=8.0.3,<9.0.0)
